{
  "content":
    [
      {
        "platy-MS-7C02":
          {
            "0":
              {
                "26354": 0.93682086467743
              },
            "1":
              {
                "26367": 0.48517534136772
              },
            "2":
              {
                "26368": 0.46695360541344
              },
            "3":
              {
                "26369": 0.44233882427216
              },
            "4":
              {
                "26370": 0.50137603282928
              },
            "5":
              {
                "26371": 0.49770650267601
              }
          }
      },
      {
        "platy-MS-7C02":
          {
            "0":
              {
                "26354": 0.57137894630432
              },
            "1":
              {
                "26367": 0.99416255950928
              },
            "2":
              {
                "26368": 0.91064161062241
              },
            "3":
              {
                "26369": 0.9595752954483
              },
            "4":
              {
                "26370": 0.99161320924759
              },
            "5":
              {
                "26371": 0.94079065322876
              }
          }
      },
      {
        "platy-MS-7C02":
          {
            "0":
              {
                "26354": 0.99386656284332
              },
            "1":
              {
                "26367": 0.99416255950928
              },
            "2":
              {
                "26368": 0.99574595689774
              },
            "3":
              {
                "26369": 0.98649162054062
              },
            "4":
              {
                "26370": 0.99161320924759
              },
            "5":
              {
                "26371": 0.96966743469238
              }
          }
      },
      {
        "platy-MS-7C02":
          {
            "0":
              {
                "26354": 0.99386656284332
              },
            "1":
              {
                "26367": 0.99416255950928
              },
            "2":
              {
                "26368": 0.99574595689774
              },
            "3":
              {
                "26369": 0.98649162054062
              },
            "4":
              {
                "26370": 0.99161320924759
              },
            "5":
              {
                "26371": 0.96834391355515
              }
          }
      },
      {
        "platy-MS-7C02":
          {
            "0":
              {
                "26354": 0.99386656284332
              },
            "1":
              {
                "26367": 0.99416255950928
              },
            "2":
              {
                "26368": 0.99574595689774
              },
            "3":
              {
                "26369": 0.98649162054062
              },
            "4":
              {
                "26370": 0.99161320924759
              },
            "5":
              {
                "26371": 0.96867311000824
              }
          }
      },
      {
        "platy-MS-7C02":
          {
            "0":
              {
                "26354": 0.99386656284332
              },
            "1":
              {
                "26367": 0.99416255950928
              },
            "2":
              {
                "26368": 0.99574595689774
              },
            "3":
              {
                "26369": 0.98649162054062
              },
            "4":
              {
                "26370": 0.99161320924759
              },
            "5":
              {
                "26371": 0.92858922481537
              }
          }
      },
      {
        "platy-MS-7C02":
          {
            "0":
              {
                "26354": 0.95166724920273
              },
            "1":
              {
                "26367": 0.93488162755966
              },
            "2":
              {
                "26368": 0.80858415365219
              },
            "3":
              {
                "26369": 0.91024947166443
              },
            "4":
              {
                "26370": 0.43991619348526
              },
            "5":
              {
                "26371": 0.69497299194336
              }
          }
      },
      {
        "platy-MS-7C02":
          {
            "0":
              {
                "26354": 0.97964024543762
              },
            "1":
              {
                "26367": 0.99388861656189
              },
            "2":
              {
                "26368": 0.99514925479889
              },
            "3":
              {
                "26369": 0.99606591463089
              },
            "4":
              {
                "26370": 0.99323058128357
              },
            "5":
              {
                "26371": 0.94908976554871
              }
          }
      },
      {
        "platy-MS-7C02":
          {
            "0":
              {
                "26354": 0.91721630096436
              },
            "1":
              {
                "26367": 0.99388861656189
              },
            "2":
              {
                "26368": 0.99514925479889
              },
            "3":
              {
                "26369": 0.99606591463089
              },
            "4":
              {
                "26370": 0.99323058128357
              },
            "5":
              {
                "26371": 0.96623200178146
              }
          }
      },
      {
        "platy-MS-7C02":
          {
            "0":
              {
                "26354": 0.31121981143951
              },
            "1":
              {
                "26367": 0.99388861656189
              },
            "2":
              {
                "26368": 0.99514925479889
              },
            "3":
              {
                "26369": 0.99606591463089
              },
            "4":
              {
                "26370": 0.99323058128357
              },
            "5":
              {
                "26371": 0.96964710950851
              }
          }
      },
      {
        "platy-MS-7C02":
          {
            "0":
              {
                "26354": 0.6583000421524
              },
            "1":
              {
                "26367": 0.99388861656189
              },
            "2":
              {
                "26368": 0.99514925479889
              },
            "3":
              {
                "26369": 0.99606591463089
              },
            "4":
              {
                "26370": 0.99323058128357
              },
            "5":
              {
                "26371": 0.85080724954605
              }
          }
      },
      {
        "platy-MS-7C02":
          {
            "0":
              {
                "26354": 0.99727559089661
              },
            "1":
              {
                "26367": 0.99388861656189
              },
            "2":
              {
                "26368": 0.99514925479889
              },
            "3":
              {
                "26369": 0.99606591463089
              },
            "4":
              {
                "26370": 0.99323058128357
              },
            "5":
              {
                "26371": 0.90986621379852
              }
          }
      },
      {
        "platy-MS-7C02":
          {
            "0":
              {
                "26354": 0.99727559089661
              },
            "1":
              {
                "26367": 0.99388861656189
              },
            "2":
              {
                "26368": 0.99514925479889
              },
            "3":
              {
                "26369": 0.99606591463089
              },
            "4":
              {
                "26370": 0.99323058128357
              },
            "5":
              {
                "26371": 0.88067102432251
              }
          }
      },
      {
        "platy-MS-7C02":
          {
            "0":
              {
                "26354": 0.99727559089661
              },
            "1":
              {
                "26367": 0.99388861656189
              },
            "2":
              {
                "26368": 0.99514925479889
              },
            "3":
              {
                "26369": 0.99606591463089
              },
            "4":
              {
                "26370": 0.99323058128357
              },
            "5":
              {
                "26371": 0.91034650802612
              }
          }
      },
      {
        "platy-MS-7C02":
          {
            "0":
              {
                "26354": 0.99727559089661
              },
            "1":
              {
                "26367": 0.99388861656189
              },
            "2":
              {
                "26368": 0.99514925479889
              },
            "3":
              {
                "26369": 0.99606591463089
              },
            "4":
              {
                "26370": 0.99323058128357
              },
            "5":
              {
                "26371": 0.93839573860168
              }
          }
      },
      {
        "platy-MS-7C02":
          {
            "0":
              {
                "26354": 0.99727559089661
              },
            "1":
              {
                "26367": 0.99388861656189
              },
            "2":
              {
                "26368": 0.99514925479889
              },
            "3":
              {
                "26369": 0.99606591463089
              },
            "4":
              {
                "26370": 0.99323058128357
              },
            "5":
              {
                "26371": 0.88023382425308
              }
          }
      },
      {
        "platy-MS-7C02":
          {
            "0":
              {
                "26354": 0.99727559089661
              },
            "1":
              {
                "26367": 0.99388861656189
              },
            "2":
              {
                "26368": 0.99514925479889
              },
            "3":
              {
                "26369": 0.99606591463089
              },
            "4":
              {
                "26370": 0.99323058128357
              },
            "5":
              {
                "26371": 0.91275173425674
              }
          }
      },
      {
        "platy-MS-7C02":
          {
            "0":
              {
                "26354": 0.99727559089661
              },
            "1":
              {
                "26367": 0.99388861656189
              },
            "2":
              {
                "26368": 0.99514925479889
              },
            "3":
              {
                "26369": 0.99606591463089
              },
            "4":
              {
                "26370": 0.99323058128357
              },
            "5":
              {
                "26371": 0.96389180421829
              }
          }
      },
      {
        "platy-MS-7C02":
          {
            "0":
              {
                "26354": 0.99727559089661
              },
            "1":
              {
                "26367": 0.99388861656189
              },
            "2":
              {
                "26368": 0.99514925479889
              },
            "3":
              {
                "26369": 0.99606591463089
              },
            "4":
              {
                "26370": 0.99323058128357
              },
            "5":
              {
                "26371": 0.91759914159775
              }
          }
      },
      {
        "platy-MS-7C02":
          {
            "0":
              {
                "26354": 0.99727559089661
              },
            "1":
              {
                "26367": 0.99388861656189
              },
            "2":
              {
                "26368": 0.99514925479889
              },
            "3":
              {
                "26369": 0.99606591463089
              },
            "4":
              {
                "26370": 0.99323058128357
              },
            "5":
              {
                "26371": 0.90537679195404
              }
          }
      },
      {
        "platy-MS-7C02":
          {
            "0":
              {
                "26354": 0.99727559089661
              },
            "1":
              {
                "26367": 0.99388861656189
              },
            "2":
              {
                "26368": 0.99514925479889
              },
            "3":
              {
                "26369": 0.99606591463089
              },
            "4":
              {
                "26370": 0.99323058128357
              },
            "5":
              {
                "26371": 0.93561351299286
              }
          }
      },
      {
        "platy-MS-7C02":
          {
            "0":
              {
                "26354": 0.99727559089661
              },
            "1":
              {
                "26367": 0.96325647830963
              },
            "2":
              {
                "26368": 0.99514925479889
              },
            "3":
              {
                "26369": 0.99606591463089
              },
            "4":
              {
                "26370": 0.87717843055725
              },
            "5":
              {
                "26371": 0.93794369697571
              }
          }
      },
      {
        "platy-MS-7C02":
          {
            "0":
              {
                "26354": 0.99727559089661
              },
            "1":
              {
                "26367": 0.9953761100769
              },
            "2":
              {
                "26368": 0.99514925479889
              },
            "3":
              {
                "26369": 0.99606591463089
              },
            "4":
              {
                "26370": 0.982017993927
              },
            "5":
              {
                "26371": 0.93782198429108
              }
          }
      },
      {
        "platy-MS-7C02":
          {
            "0":
              {
                "26354": 0.99727559089661
              },
            "1":
              {
                "26367": 0.9953761100769
              },
            "2":
              {
                "26368": 0.95307528972626
              },
            "3":
              {
                "26369": 0.99606591463089
              },
            "4":
              {
                "26370": 0.99695283174515
              },
            "5":
              {
                "26371": 0.93864113092422
              }
          }
      },
      {
        "platy-MS-7C02":
          {
            "0":
              {
                "26354": 0.99727559089661
              },
            "1":
              {
                "26367": 0.9953761100769
              },
            "2":
              {
                "26368": 0.9953470826149
              },
            "3":
              {
                "26369": 0.99606591463089
              },
            "4":
              {
                "26370": 0.99695283174515
              },
            "5":
              {
                "26371": 0.91106873750687
              }
          }
      },
      {
        "platy-MS-7C02":
          {
            "0":
              {
                "26354": 0.99727559089661
              },
            "1":
              {
                "26367": 0.9953761100769
              },
            "2":
              {
                "26368": 0.9953470826149
              },
            "3":
              {
                "26369": 0.99606591463089
              },
            "4":
              {
                "26370": 0.99695283174515
              },
            "5":
              {
                "26371": 0.88249826431274
              }
          }
      },
      {
        "platy-MS-7C02":
          {
            "0":
              {
                "26354": 0.99727559089661
              },
            "1":
              {
                "26367": 0.9953761100769
              },
            "2":
              {
                "26368": 0.9953470826149
              },
            "3":
              {
                "26369": 0.99606591463089
              },
            "4":
              {
                "26370": 0.99695283174515
              },
            "5":
              {
                "26371": 0.88274013996124
              }
          }
      },
      {
        "platy-MS-7C02":
          {
            "0":
              {
                "26354": 0.99727559089661
              },
            "1":
              {
                "26367": 0.9953761100769
              },
            "2":
              {
                "26368": 0.9953470826149
              },
            "3":
              {
                "26369": 0.99606591463089
              },
            "4":
              {
                "26370": 0.99695283174515
              },
            "5":
              {
                "26371": 0.91057294607162
              }
          }
      },
      {
        "platy-MS-7C02":
          {
            "0":
              {
                "26354": 0.99727559089661
              },
            "1":
              {
                "26367": 0.9953761100769
              },
            "2":
              {
                "26368": 0.9953470826149
              },
            "3":
              {
                "26369": 0.99606591463089
              },
            "4":
              {
                "26370": 0.99695283174515
              },
            "5":
              {
                "26371": 0.93900126218796
              }
          }
      },
      {
        "platy-MS-7C02":
          {
            "0":
              {
                "26354": 0.99727559089661
              },
            "1":
              {
                "26367": 0.9953761100769
              },
            "2":
              {
                "26368": 0.9953470826149
              },
            "3":
              {
                "26369": 0.99606591463089
              },
            "4":
              {
                "26370": 0.99695283174515
              },
            "5":
              {
                "26371": 0.9103222489357
              }
          }
      },
      {
        "platy-MS-7C02":
          {
            "0":
              {
                "26354": 0.99727559089661
              },
            "1":
              {
                "26367": 0.9953761100769
              },
            "2":
              {
                "26368": 0.9953470826149
              },
            "3":
              {
                "26369": 0.99606591463089
              },
            "4":
              {
                "26370": 0.99695283174515
              },
            "5":
              {
                "26371": 0.93902790546417
              }
          }
      },
      {
        "platy-MS-7C02":
          {
            "0":
              {
                "26354": 0.99727559089661
              },
            "1":
              {
                "26367": 0.9953761100769
              },
            "2":
              {
                "26368": 0.9953470826149
              },
            "3":
              {
                "26369": 0.99606591463089
              },
            "4":
              {
                "26370": 0.99695283174515
              },
            "5":
              {
                "26371": 0.91035664081573
              }
          }
      },
      {
        "platy-MS-7C02":
          {
            "0":
              {
                "26354": 0.99727559089661
              },
            "1":
              {
                "26367": 0.9953761100769
              },
            "2":
              {
                "26368": 0.9953470826149
              },
            "3":
              {
                "26369": 0.99606591463089
              },
            "4":
              {
                "26370": 0.99695283174515
              },
            "5":
              {
                "26371": 0.93927186727524
              }
          }
      },
      {
        "platy-MS-7C02":
          {
            "0":
              {
                "26354": 0.99727559089661
              },
            "1":
              {
                "26367": 0.9953761100769
              },
            "2":
              {
                "26368": 0.9953470826149
              },
            "3":
              {
                "26369": 0.99606591463089
              },
            "4":
              {
                "26370": 0.99695283174515
              },
            "5":
              {
                "26371": 0.93921196460724
              }
          }
      },
      {
        "platy-MS-7C02":
          {
            "0":
              {
                "26354": 0.99727559089661
              },
            "1":
              {
                "26367": 0.9953761100769
              },
            "2":
              {
                "26368": 0.9953470826149
              },
            "3":
              {
                "26369": 0.93453413248062
              },
            "4":
              {
                "26370": 0.99695283174515
              },
            "5":
              {
                "26371": 0.93893545866013
              }
          }
      },
      {
        "platy-MS-7C02":
          {
            "0":
              {
                "26354": 0.99727559089661
              },
            "1":
              {
                "26367": 0.9953761100769
              },
            "2":
              {
                "26368": 0.9953470826149
              },
            "3":
              {
                "26369": 0.99695980548859
              },
            "4":
              {
                "26370": 0.99695283174515
              },
            "5":
              {
                "26371": 0.91093772649765
              }
          }
      },
      {
        "platy-MS-7C02":
          {
            "0":
              {
                "26354": 0.99727559089661
              },
            "1":
              {
                "26367": 0.9953761100769
              },
            "2":
              {
                "26368": 0.9953470826149
              },
            "3":
              {
                "26369": 0.99695980548859
              },
            "4":
              {
                "26370": 0.99695283174515
              },
            "5":
              {
                "26371": 0.92453110218048
              }
          }
      },
      {
        "platy-MS-7C02":
          {
            "0":
              {
                "26354": 0.99727559089661
              },
            "1":
              {
                "26367": 0.9953761100769
              },
            "2":
              {
                "26368": 0.9953470826149
              },
            "3":
              {
                "26369": 0.99695980548859
              },
            "4":
              {
                "26370": 0.99695283174515
              },
            "5":
              {
                "26371": 0.92740744352341
              }
          }
      },
      {
        "platy-MS-7C02":
          {
            "0":
              {
                "26354": 0.99727559089661
              },
            "1":
              {
                "26367": 0.9953761100769
              },
            "2":
              {
                "26368": 0.9953470826149
              },
            "3":
              {
                "26369": 0.99695980548859
              },
            "4":
              {
                "26370": 0.99695283174515
              },
            "5":
              {
                "26371": 0.94006454944611
              }
          }
      },
      {
        "platy-MS-7C02":
          {
            "0":
              {
                "26354": 0.99727559089661
              },
            "1":
              {
                "26367": 0.9953761100769
              },
            "2":
              {
                "26368": 0.9953470826149
              },
            "3":
              {
                "26369": 0.99695980548859
              },
            "4":
              {
                "26370": 0.99695283174515
              },
            "5":
              {
                "26371": 0.93946707248688
              }
          }
      },
      {
        "platy-MS-7C02":
          {
            "0":
              {
                "26354": 0.99727559089661
              },
            "1":
              {
                "26367": 0.9953761100769
              },
            "2":
              {
                "26368": 0.9953470826149
              },
            "3":
              {
                "26369": 0.99695980548859
              },
            "4":
              {
                "26370": 0.99695283174515
              },
            "5":
              {
                "26371": 0.88292717933655
              }
          }
      },
      {
        "platy-MS-7C02":
          {
            "0":
              {
                "26354": 0.99727559089661
              },
            "1":
              {
                "26367": 0.9953761100769
              },
            "2":
              {
                "26368": 0.9953470826149
              },
            "3":
              {
                "26369": 0.99695980548859
              },
            "4":
              {
                "26370": 0.99695283174515
              },
            "5":
              {
                "26371": 0.911037504673
              }
          }
      },
      {
        "platy-MS-7C02":
          {
            "0":
              {
                "26354": 0.99727559089661
              },
            "1":
              {
                "26367": 0.9953761100769
              },
            "2":
              {
                "26368": 0.9953470826149
              },
            "3":
              {
                "26369": 0.99695980548859
              },
            "4":
              {
                "26370": 0.99695283174515
              },
            "5":
              {
                "26371": 0.91150045394897
              }
          }
      },
      {
        "platy-MS-7C02":
          {
            "0":
              {
                "26354": 0.99727559089661
              },
            "1":
              {
                "26367": 0.9953761100769
              },
            "2":
              {
                "26368": 0.9953470826149
              },
            "3":
              {
                "26369": 0.99695980548859
              },
            "4":
              {
                "26370": 0.99695283174515
              },
            "5":
              {
                "26371": 0.9403412938118
              }
          }
      },
      {
        "platy-MS-7C02":
          {
            "0":
              {
                "26354": 0.99727559089661
              },
            "1":
              {
                "26367": 0.9953761100769
              },
            "2":
              {
                "26368": 0.9953470826149
              },
            "3":
              {
                "26369": 0.99695980548859
              },
            "4":
              {
                "26370": 0.99695283174515
              },
            "5":
              {
                "26371": 0.90345948934555
              }
          }
      },
      {
        "platy-MS-7C02":
          {
            "0":
              {
                "26354": 0.99727559089661
              },
            "1":
              {
                "26367": 0.9953761100769
              },
            "2":
              {
                "26368": 0.9953470826149
              },
            "3":
              {
                "26369": 0.99695980548859
              },
            "4":
              {
                "26370": 0.99695283174515
              },
            "5":
              {
                "26371": 0.89190953969955
              }
          }
      },
      {
        "platy-MS-7C02":
          {
            "0":
              {
                "26354": 0.99727559089661
              },
            "1":
              {
                "26367": 0.92879843711853
              },
            "2":
              {
                "26368": 0.9953470826149
              },
            "3":
              {
                "26369": 0.99695980548859
              },
            "4":
              {
                "26370": 0.82982712984085
              },
            "5":
              {
                "26371": 0.92336046695709
              }
          }
      },
      {
        "platy-MS-7C02":
          {
            "0":
              {
                "26354": 0.96862405538559
              },
            "1":
              {
                "26367": 0.99675953388214
              },
            "2":
              {
                "26368": 0.9953470826149
              },
            "3":
              {
                "26369": 0.99695980548859
              },
            "4":
              {
                "26370": 0.96696835756302
              },
            "5":
              {
                "26371": 0.87428665161133
              }
          }
      },
      {
        "platy-MS-7C02":
          {
            "0":
              {
                "26354": 0.99601137638092
              },
            "1":
              {
                "26367": 0.99675953388214
              },
            "2":
              {
                "26368": 0.9953470826149
              },
            "3":
              {
                "26369": 0.99695980548859
              },
            "4":
              {
                "26370": 0.933469414711
              },
            "5":
              {
                "26371": 0.88014447689056
              }
          }
      },
      {
        "platy-MS-7C02":
          {
            "0":
              {
                "26354": 0.99601137638092
              },
            "1":
              {
                "26367": 0.99675953388214
              },
            "2":
              {
                "26368": 0.9953470826149
              },
            "3":
              {
                "26369": 0.99695980548859
              },
            "4":
              {
                "26370": 0.95016151666641
              },
            "5":
              {
                "26371": 0.88065224885941
              }
          }
      },
      {
        "platy-MS-7C02":
          {
            "0":
              {
                "26354": 0.99601137638092
              },
            "1":
              {
                "26367": 0.99675953388214
              },
            "2":
              {
                "26368": 0.9953470826149
              },
            "3":
              {
                "26369": 0.99695980548859
              },
            "4":
              {
                "26370": 0.99552470445633
              },
            "5":
              {
                "26371": 0.91023290157318
              }
          }
      },
      {
        "platy-MS-7C02":
          {
            "0":
              {
                "26354": 0.99601137638092
              },
            "1":
              {
                "26367": 0.99675953388214
              },
            "2":
              {
                "26368": 0.96626287698746
              },
            "3":
              {
                "26369": 0.99695980548859
              },
            "4":
              {
                "26370": 0.99552470445633
              },
            "5":
              {
                "26371": 0.93989127874374
              }
          }
      },
      {
        "platy-MS-7C02":
          {
            "0":
              {
                "26354": 0.99601137638092
              },
            "1":
              {
                "26367": 0.99675953388214
              },
            "2":
              {
                "26368": 0.99455809593201
              },
            "3":
              {
                "26369": 0.99695980548859
              },
            "4":
              {
                "26370": 0.99552470445633
              },
            "5":
              {
                "26371": 0.96270829439163
              }
          }
      },
      {
        "platy-MS-7C02":
          {
            "0":
              {
                "26354": 0.99601137638092
              },
            "1":
              {
                "26367": 0.99675953388214
              },
            "2":
              {
                "26368": 0.99455809593201
              },
            "3":
              {
                "26369": 0.99695980548859
              },
            "4":
              {
                "26370": 0.99552470445633
              },
            "5":
              {
                "26371": 0.96114933490753
              }
          }
      },
      {
        "platy-MS-7C02":
          {
            "0":
              {
                "26354": 0.99601137638092
              },
            "1":
              {
                "26367": 0.99675953388214
              },
            "2":
              {
                "26368": 0.99455809593201
              },
            "3":
              {
                "26369": 0.99695980548859
              },
            "4":
              {
                "26370": 0.99552470445633
              },
            "5":
              {
                "26371": 0.90848082304001
              }
          }
      },
      {
        "platy-MS-7C02":
          {
            "0":
              {
                "26354": 0.99601137638092
              },
            "1":
              {
                "26367": 0.99675953388214
              },
            "2":
              {
                "26368": 0.99455809593201
              },
            "3":
              {
                "26369": 0.99695980548859
              },
            "4":
              {
                "26370": 0.99552470445633
              },
            "5":
              {
                "26371": 0.94027757644653
              }
          }
      },
      {
        "platy-MS-7C02":
          {
            "0":
              {
                "26354": 0.96819460391998
              },
            "1":
              {
                "26367": 0.99675953388214
              },
            "2":
              {
                "26368": 0.99455809593201
              },
            "3":
              {
                "26369": 0.99695980548859
              },
            "4":
              {
                "26370": 0.99552470445633
              },
            "5":
              {
                "26371": 0.91023921966553
              }
          }
      },
      {
        "platy-MS-7C02":
          {
            "0":
              {
                "26354": 0.99656426906586
              },
            "1":
              {
                "26367": 0.99675953388214
              },
            "2":
              {
                "26368": 0.99455809593201
              },
            "3":
              {
                "26369": 0.99695980548859
              },
            "4":
              {
                "26370": 0.99552470445633
              },
            "5":
              {
                "26371": 0.93995940685272
              }
          }
      },
      {
        "platy-MS-7C02":
          {
            "0":
              {
                "26354": 0.99656426906586
              },
            "1":
              {
                "26367": 0.99675953388214
              },
            "2":
              {
                "26368": 0.99455809593201
              },
            "3":
              {
                "26369": 0.99695980548859
              },
            "4":
              {
                "26370": 0.99552470445633
              },
            "5":
              {
                "26371": 0.91185653209686
              }
          }
      },
      {
        "platy-MS-7C02":
          {
            "0":
              {
                "26354": 0.99656426906586
              },
            "1":
              {
                "26367": 0.99675953388214
              },
            "2":
              {
                "26368": 0.99455809593201
              },
            "3":
              {
                "26369": 0.99695980548859
              },
            "4":
              {
                "26370": 0.99552470445633
              },
            "5":
              {
                "26371": 0.91171783208847
              }
          }
      },
      {
        "platy-MS-7C02":
          {
            "0":
              {
                "26354": 0.99656426906586
              },
            "1":
              {
                "26367": 0.99675953388214
              },
            "2":
              {
                "26368": 0.99455809593201
              },
            "3":
              {
                "26369": 0.99695980548859
              },
            "4":
              {
                "26370": 0.99552470445633
              },
            "5":
              {
                "26371": 0.93645626306534
              }
          }
      },
      {
        "platy-MS-7C02":
          {
            "0":
              {
                "26354": 0.99656426906586
              },
            "1":
              {
                "26367": 0.90855813026428
              },
            "2":
              {
                "26368": 0.99455809593201
              },
            "3":
              {
                "26369": 0.99695980548859
              },
            "4":
              {
                "26370": 0.99552470445633
              },
            "5":
              {
                "26371": 0.93747371435165
              }
          }
      },
      {
        "platy-MS-7C02":
          {
            "0":
              {
                "26354": 0.99656426906586
              },
            "1":
              {
                "26367": 0.99695014953613
              },
            "2":
              {
                "26368": 0.99455809593201
              },
            "3":
              {
                "26369": 0.99695980548859
              },
            "4":
              {
                "26370": 0.99552470445633
              },
            "5":
              {
                "26371": 0.9118430018425
              }
          }
      },
      {
        "platy-MS-7C02":
          {
            "0":
              {
                "26354": 0.99656426906586
              },
            "1":
              {
                "26367": 0.99695014953613
              },
            "2":
              {
                "26368": 0.99455809593201
              },
            "3":
              {
                "26369": 0.99695980548859
              },
            "4":
              {
                "26370": 0.99552470445633
              },
            "5":
              {
                "26371": 0.91045606136322
              }
          }
      },
      {
        "platy-MS-7C02":
          {
            "0":
              {
                "26354": 0.99656426906586
              },
            "1":
              {
                "26367": 0.99695014953613
              },
            "2":
              {
                "26368": 0.99455809593201
              },
            "3":
              {
                "26369": 0.99695980548859
              },
            "4":
              {
                "26370": 0.99552470445633
              },
            "5":
              {
                "26371": 0.93837404251099
              }
          }
      },
      {
        "platy-MS-7C02":
          {
            "0":
              {
                "26354": 0.99656426906586
              },
            "1":
              {
                "26367": 0.99695014953613
              },
            "2":
              {
                "26368": 0.99455809593201
              },
            "3":
              {
                "26369": 0.99695980548859
              },
            "4":
              {
                "26370": 0.99552470445633
              },
            "5":
              {
                "26371": 0.91115069389343
              }
          }
      },
      {
        "platy-MS-7C02":
          {
            "0":
              {
                "26354": 0.99656426906586
              },
            "1":
              {
                "26367": 0.99695014953613
              },
            "2":
              {
                "26368": 0.99455809593201
              },
            "3":
              {
                "26369": 0.99695980548859
              },
            "4":
              {
                "26370": 0.99552470445633
              },
            "5":
              {
                "26371": 0.91099494695663
              }
          }
      },
      {
        "platy-MS-7C02":
          {
            "0":
              {
                "26354": 0.99656426906586
              },
            "1":
              {
                "26367": 0.99695014953613
              },
            "2":
              {
                "26368": 0.99455809593201
              },
            "3":
              {
                "26369": 0.99695980548859
              },
            "4":
              {
                "26370": 0.99552470445633
              },
            "5":
              {
                "26371": 0.91088342666626
              }
          }
      },
      {
        "platy-MS-7C02":
          {
            "0":
              {
                "26354": 0.99656426906586
              },
            "1":
              {
                "26367": 0.99695014953613
              },
            "2":
              {
                "26368": 0.99455809593201
              },
            "3":
              {
                "26369": 0.99695980548859
              },
            "4":
              {
                "26370": 0.99552470445633
              },
            "5":
              {
                "26371": 0.91001468896866
              }
          }
      },
      {
        "platy-MS-7C02":
          {
            "0":
              {
                "26354": 0.99656426906586
              },
            "1":
              {
                "26367": 0.99695014953613
              },
            "2":
              {
                "26368": 0.99455809593201
              },
            "3":
              {
                "26369": 0.99695980548859
              },
            "4":
              {
                "26370": 0.99552470445633
              },
            "5":
              {
                "26371": 0.91190212965012
              }
          }
      },
      {
        "platy-MS-7C02":
          {
            "0":
              {
                "26354": 0.99656426906586
              },
            "1":
              {
                "26367": 0.99695014953613
              },
            "2":
              {
                "26368": 0.99455809593201
              },
            "3":
              {
                "26369": 0.99695980548859
              },
            "4":
              {
                "26370": 0.99552470445633
              },
            "5":
              {
                "26371": 0.93908673524857
              }
          }
      },
      {
        "platy-MS-7C02":
          {
            "0":
              {
                "26354": 0.99656426906586
              },
            "1":
              {
                "26367": 0.99695014953613
              },
            "2":
              {
                "26368": 0.99455809593201
              },
            "3":
              {
                "26369": 0.99695980548859
              },
            "4":
              {
                "26370": 0.99552470445633
              },
            "5":
              {
                "26371": 0.91080063581467
              }
          }
      },
      {
        "platy-MS-7C02":
          {
            "0":
              {
                "26354": 0.99656426906586
              },
            "1":
              {
                "26367": 0.99695014953613
              },
            "2":
              {
                "26368": 0.99455809593201
              },
            "3":
              {
                "26369": 0.99695980548859
              },
            "4":
              {
                "26370": 0.99552470445633
              },
            "5":
              {
                "26371": 0.94026750326157
              }
          }
      },
      {
        "platy-MS-7C02":
          {
            "0":
              {
                "26354": 0.99656426906586
              },
            "1":
              {
                "26367": 0.99695014953613
              },
            "2":
              {
                "26368": 0.99455809593201
              },
            "3":
              {
                "26369": 0.99695980548859
              },
            "4":
              {
                "26370": 0.99552470445633
              },
            "5":
              {
                "26371": 0.88350886106491
              }
          }
      },
      {
        "platy-MS-7C02":
          {
            "0":
              {
                "26354": 0.99656426906586
              },
            "1":
              {
                "26367": 0.99695014953613
              },
            "2":
              {
                "26368": 0.99455809593201
              },
            "3":
              {
                "26369": 0.99695980548859
              },
            "4":
              {
                "26370": 0.99552470445633
              },
            "5":
              {
                "26371": 0.91180193424225
              }
          }
      },
      {
        "platy-MS-7C02":
          {
            "0":
              {
                "26354": 0.99656426906586
              },
            "1":
              {
                "26367": 0.99695014953613
              },
            "2":
              {
                "26368": 0.99455809593201
              },
            "3":
              {
                "26369": 0.99695980548859
              },
            "4":
              {
                "26370": 0.99552470445633
              },
            "5":
              {
                "26371": 0.93924081325531
              }
          }
      },
      {
        "platy-MS-7C02":
          {
            "0":
              {
                "26354": 0.99656426906586
              },
            "1":
              {
                "26367": 0.99695014953613
              },
            "2":
              {
                "26368": 0.99455809593201
              },
            "3":
              {
                "26369": 0.99695980548859
              },
            "4":
              {
                "26370": 0.99552470445633
              },
            "5":
              {
                "26371": 0.93958204984665
              }
          }
      },
      {
        "platy-MS-7C02":
          {
            "0":
              {
                "26354": 0.99656426906586
              },
            "1":
              {
                "26367": 0.99695014953613
              },
            "2":
              {
                "26368": 0.99455809593201
              },
            "3":
              {
                "26369": 0.99695980548859
              },
            "4":
              {
                "26370": 0.99552470445633
              },
            "5":
              {
                "26371": 0.94027656316757
              }
          }
      },
      {
        "platy-MS-7C02":
          {
            "0":
              {
                "26354": 0.99656426906586
              },
            "1":
              {
                "26367": 0.99695014953613
              },
            "2":
              {
                "26368": 0.99455809593201
              },
            "3":
              {
                "26369": 0.89510858058929
              },
            "4":
              {
                "26370": 0.99552470445633
              },
            "5":
              {
                "26371": 0.88342636823654
              }
          }
      },
      {
        "platy-MS-7C02":
          {
            "0":
              {
                "26354": 0.99656426906586
              },
            "1":
              {
                "26367": 0.99695014953613
              },
            "2":
              {
                "26368": 0.94642013311386
              },
            "3":
              {
                "26369": 0.99498122930527
              },
            "4":
              {
                "26370": 0.99552470445633
              },
            "5":
              {
                "26371": 0.94007575511932
              }
          }
      },
      {
        "platy-MS-7C02":
          {
            "0":
              {
                "26354": 0.99656426906586
              },
            "1":
              {
                "26367": 0.99695014953613
              },
            "2":
              {
                "26368": 0.99372917413712
              },
            "3":
              {
                "26369": 0.99498122930527
              },
            "4":
              {
                "26370": 0.86571174860001
              },
            "5":
              {
                "26371": 0.93956702947617
              }
          }
      },
      {
        "platy-MS-7C02":
          {
            "0":
              {
                "26354": 0.99656426906586
              },
            "1":
              {
                "26367": 0.99695014953613
              },
            "2":
              {
                "26368": 0.99372917413712
              },
            "3":
              {
                "26369": 0.99498122930527
              },
            "4":
              {
                "26370": 0.99598598480225
              },
            "5":
              {
                "26371": 0.88962805271149
              }
          }
      },
      {
        "platy-MS-7C02":
          {
            "0":
              {
                "26354": 0.99656426906586
              },
            "1":
              {
                "26367": 0.99695014953613
              },
            "2":
              {
                "26368": 0.99372917413712
              },
            "3":
              {
                "26369": 0.99498122930527
              },
            "4":
              {
                "26370": 0.99598598480225
              },
            "5":
              {
                "26371": 0.90503311157227
              }
          }
      },
      {
        "platy-MS-7C02":
          {
            "0":
              {
                "26354": 0.99656426906586
              },
            "1":
              {
                "26367": 0.99695014953613
              },
            "2":
              {
                "26368": 0.99372917413712
              },
            "3":
              {
                "26369": 0.99498122930527
              },
            "4":
              {
                "26370": 0.99598598480225
              },
            "5":
              {
                "26371": 0.94036334753036
              }
          }
      },
      {
        "platy-MS-7C02":
          {
            "0":
              {
                "26354": 0.99656426906586
              },
            "1":
              {
                "26367": 0.99695014953613
              },
            "2":
              {
                "26368": 0.99372917413712
              },
            "3":
              {
                "26369": 0.99498122930527
              },
            "4":
              {
                "26370": 0.99598598480225
              },
            "5":
              {
                "26371": 0.91198885440826
              }
          }
      },
      {
        "platy-MS-7C02":
          {
            "0":
              {
                "26354": 0.99656426906586
              },
            "1":
              {
                "26367": 0.99695014953613
              },
            "2":
              {
                "26368": 0.99372917413712
              },
            "3":
              {
                "26369": 0.99498122930527
              },
            "4":
              {
                "26370": 0.99598598480225
              },
            "5":
              {
                "26371": 0.94033652544022
              }
          }
      },
      {
        "platy-MS-7C02":
          {
            "0":
              {
                "26354": 0.99656426906586
              },
            "1":
              {
                "26367": 0.99695014953613
              },
            "2":
              {
                "26368": 0.99372917413712
              },
            "3":
              {
                "26369": 0.99498122930527
              },
            "4":
              {
                "26370": 0.99598598480225
              },
            "5":
              {
                "26371": 0.90841209888458
              }
          }
      },
      {
        "platy-MS-7C02":
          {
            "0":
              {
                "26354": 0.99656426906586
              },
            "1":
              {
                "26367": 0.99695014953613
              },
            "2":
              {
                "26368": 0.99372917413712
              },
            "3":
              {
                "26369": 0.99498122930527
              },
            "4":
              {
                "26370": 0.99598598480225
              },
            "5":
              {
                "26371": 0.94002324342728
              }
          }
      },
      {
        "platy-MS-7C02":
          {
            "0":
              {
                "26354": 0.99656426906586
              },
            "1":
              {
                "26367": 0.99695014953613
              },
            "2":
              {
                "26368": 0.99372917413712
              },
            "3":
              {
                "26369": 0.99498122930527
              },
            "4":
              {
                "26370": 0.99598598480225
              },
            "5":
              {
                "26371": 0.91201758384705
              }
          }
      },
      {
        "platy-MS-7C02":
          {
            "0":
              {
                "26354": 0.99656426906586
              },
            "1":
              {
                "26367": 0.99695014953613
              },
            "2":
              {
                "26368": 0.96258300542831
              },
            "3":
              {
                "26369": 0.99498122930527
              },
            "4":
              {
                "26370": 0.99598598480225
              },
            "5":
              {
                "26371": 0.9400874376297
              }
          }
      },
      {
        "platy-MS-7C02":
          {
            "0":
              {
                "26354": 0.99656426906586
              },
            "1":
              {
                "26367": 0.99695014953613
              },
            "2":
              {
                "26368": 0.99012112617493
              },
            "3":
              {
                "26369": 0.99498122930527
              },
            "4":
              {
                "26370": 0.99598598480225
              },
            "5":
              {
                "26371": 0.91190594434738
              }
          }
      },
      {
        "platy-MS-7C02":
          {
            "0":
              {
                "26354": 0.99656426906586
              },
            "1":
              {
                "26367": 0.99695014953613
              },
            "2":
              {
                "26368": 0.99012112617493
              },
            "3":
              {
                "26369": 0.99498122930527
              },
            "4":
              {
                "26370": 0.9648374915123
              },
            "5":
              {
                "26371": 0.92590856552124
              }
          }
      },
      {
        "platy-MS-7C02":
          {
            "0":
              {
                "26354": 0.99656426906586
              },
            "1":
              {
                "26367": 0.99695014953613
              },
            "2":
              {
                "26368": 0.99012112617493
              },
            "3":
              {
                "26369": 0.99498122930527
              },
            "4":
              {
                "26370": 0.9744490981102
              },
            "5":
              {
                "26371": 0.93396949768066
              }
          }
      },
      {
        "platy-MS-7C02":
          {
            "0":
              {
                "26354": 0.99656426906586
              },
            "1":
              {
                "26367": 0.99695014953613
              },
            "2":
              {
                "26368": 0.99012112617493
              },
            "3":
              {
                "26369": 0.99498122930527
              },
            "4":
              {
                "26370": 0.9744490981102
              },
            "5":
              {
                "26371": 0.9106667637825
              }
          }
      },
      {
        "platy-MS-7C02":
          {
            "0":
              {
                "26354": 0.99656426906586
              },
            "1":
              {
                "26367": 0.96696919202805
              },
            "2":
              {
                "26368": 0.99012112617493
              },
            "3":
              {
                "26369": 0.99498122930527
              },
            "4":
              {
                "26370": 0.91853475570679
              },
            "5":
              {
                "26371": 0.93400663137436
              }
          }
      },
      {
        "platy-MS-7C02":
          {
            "0":
              {
                "26354": 0.99656426906586
              },
            "1":
              {
                "26367": 0.99596261978149
              },
            "2":
              {
                "26368": 0.99012112617493
              },
            "3":
              {
                "26369": 0.99498122930527
              },
            "4":
              {
                "26370": 0.94741106033325
              },
            "5":
              {
                "26371": 0.93561595678329
              }
          }
      },
      {
        "platy-MS-7C02":
          {
            "0":
              {
                "26354": 0.99656426906586
              },
            "1":
              {
                "26367": 0.99596261978149
              },
            "2":
              {
                "26368": 0.99012112617493
              },
            "3":
              {
                "26369": 0.99498122930527
              },
            "4":
              {
                "26370": 0.99412190914154
              },
            "5":
              {
                "26371": 0.91172707080841
              }
          }
      },
      {
        "platy-MS-7C02":
          {
            "0":
              {
                "26354": 0.99656426906586
              },
            "1":
              {
                "26367": 0.99596261978149
              },
            "2":
              {
                "26368": 0.99012112617493
              },
            "3":
              {
                "26369": 0.99498122930527
              },
            "4":
              {
                "26370": 0.99412190914154
              },
            "5":
              {
                "26371": 0.93859338760376
              }
          }
      },
      {
        "platy-MS-7C02":
          {
            "0":
              {
                "26354": 0.99656426906586
              },
            "1":
              {
                "26367": 0.99596261978149
              },
            "2":
              {
                "26368": 0.99012112617493
              },
            "3":
              {
                "26369": 0.99498122930527
              },
            "4":
              {
                "26370": 0.99412190914154
              },
            "5":
              {
                "26371": 0.90871101617813
              }
          }
      },
      {
        "platy-MS-7C02":
          {
            "0":
              {
                "26354": 0.94065129756927
              },
            "1":
              {
                "26367": 0.93668627738953
              },
            "2":
              {
                "26368": 0.9262056350708
              },
            "3":
              {
                "26369": 0.93237060308456
              },
            "4":
              {
                "26370": 0.93639415502548
              },
            "5":
              {
                "26371": 0.87036567926407
              }
          }
      }
    ]
}
